transformlib/__init__.py
transformlib/__main__.py
transformlib/_transformlib.py
transformlib-0.4.8.dist-info/LICENSE
transformlib-0.4.8.dist-info/METADATA
transformlib-0.4.8.dist-info/WHEEL
transformlib-0.4.8.dist-info/entry_points.txt
transformlib-0.4.8.dist-info/top_level.txt
transformlib-0.4.8.dist-info/RECORD
