Metadata-Version: 2.1
Name: transformlib
Version: 0.4.8
Summary: Enables the user to organize transformations of data as a regular Python package.
Home-page: https://github.com/laegsgaardTroels/transformlib
Author: Troels Lægsgaard
Requires-Python: >=3.10
License-File: LICENSE
Provides-Extra: all
Requires-Dist: pandas >=2.2.1 ; extra == 'all'
Provides-Extra: dev
Requires-Dist: flake8 ==3.8.3 ; extra == 'dev'
Requires-Dist: jinja2 ==3.0.0 ; extra == 'dev'
Requires-Dist: pytest-cov ; extra == 'dev'
Requires-Dist: pytest-pep8 ; extra == 'dev'
Requires-Dist: pytest ==8.0.2 ; extra == 'dev'
Requires-Dist: sphinx ==7.2.6 ; extra == 'dev'
Requires-Dist: scikit-learn ==1.4.1.post1 ; extra == 'dev'
Requires-Dist: pandas ==2.2.1 ; extra == 'dev'
Provides-Extra: pandas
Requires-Dist: pandas >=2.2.1 ; extra == 'pandas'
